[
  {
    "sentence_id": 0,
    "text": "分裂的时候你要取一个这个，我还是以这个阿拉卡为例嘛。",
    "language": "zh",
    "emotion": "neutral"
  },
  {
    "sentence_id": 1,
    "text": "哦，卡西点这个，因为这个是卡西点，这个卡西点方程这个一斐是等于这个1/2这个 gradient phi 的平方加上这个 f phi，对不对？",
    "language": "zh",
    "emotion": "neutral"
  },
  {
    "sentence_id": 2,
    "text": "这个时候你。",
    "language": "zh",
    "emotion": "neutral"
  },
  {
    "sentence_id": 3,
    "text": "你你这么去做，那这样子分裂出来，它就会出来要要a和b要去叙述，那这个东西可以可以做的就是我刚刚讲的这个，我我这个分裂，这个分裂是很随意的，就是说也不是很随意，就是说你有很多选择，所以一种选择就是就是你这里加上一个。",
    "language": "zh",
    "emotion": "neutral"
  },
  {
    "sentence_id": 4,
    "text": "你你你你你加上加上一个这个这个线性项，加这个s，s随便取，一二都都无所谓，然后这个再减下去。",
    "language": "zh",
    "emotion": "neutral"
  },
  {
    "sentence_id": 5,
    "text": "这样子分裂，这样子分裂，你这里这个L，这个L就是就是这个L就等于负的拉普拉斯加上这个，加上两倍的这个S i，对吧？",
    "language": "zh",
    "emotion": "neutral"
  },
  {
    "sentence_id": 6,
    "text": "这个L这个L出来就是这种。",
    "language": "zh",
    "emotion": "neutral"
  },
  {
    "sentence_id": 7,
    "text": "这个时候你有了一个这个有了一个这个s在这个里头的话，你你再去解这个方程，这个a b算出来就就就是就行了，你这个a b就有就有实数解。，",
    "language": "zh",
    "emotion": "neutral"
  },
  {
    "sentence_id": 8,
    "text": "大家去大家去这个去去再把这个东西过一遍，就是说你分裂的时候，你分裂的时候，你你这里取一个加一个这个线性部分，加一个线性部分。",
    "language": "zh",
    "emotion": "neutral"
  },
  {
    "sentence_id": 9,
    "text": "这样子的话，你还你解的那个方方程组，它就多了多了这一项，多了这一项就行了，多了这一项，你就你就可以把这个a b解出来，使得它这个两个方程可以这个可以解偶。",
    "language": "zh",
    "emotion": "neutral"
  },
  {
    "sentence_id": 10,
    "text": "所以这是这是刚刚这个。",
    "language": "zh",
    "emotion": "neutral"
  },
  {
    "sentence_id": 11,
    "text": "，刚刚这个四阶方程分裂成两个，分裂成两个这个二阶方程的这个这个方法。",
    "language": "zh",
    "emotion": "neutral"
  },
  {
    "sentence_id": 12,
    "text": "那么这个不光是在这里头，事实上我们要做的时候，这个东西这个东西是是必要的，这个东西是在有些情况下是确实要这么做。",
    "language": "zh",
    "emotion": "neutral"
  },
  {
    "sentence_id": 13,
    "text": "那么，对。",
    "language": "zh",
    "emotion": "neutral"
  },
  {
    "sentence_id": 14,
    "text": "哎。",
    "language": "zh",
    "emotion": "neutral"
  },
  {
    "sentence_id": 15,
    "text": "你用不用帮忙？",
    "language": "zh",
    "emotion": "neutral"
  },
  {
    "sentence_id": 16,
    "text": "哎，对对对，不把这个，大概把它拷上去。",
    "language": "zh",
    "emotion": "neutral"
  },
  {
    "sentence_id": 17,
    "text": "有事哦，没有拷，那个，OK，你你把它重启一下，待会把它拷到拷到你那个上面去。",
    "language": "zh",
    "emotion": "neutral"
  },
  {
    "sentence_id": 18,
    "text": "那个下面要讲什么东西？",
    "language": "zh",
    "emotion": "neutral"
  },
  {
    "sentence_id": 19,
    "text": "现在就是说这个是一个框架，我刚刚讲了这个这个S A V方法是一个框架，你有了这个框架以后，在这个框架下面你可以做你可以做很多事情，对吧？",
    "language": "zh",
    "emotion": "neutral"
  },
  {
    "sentence_id": 20,
    "text": "你可以做很多事情。",
    "language": "zh",
    "emotion": "neutral"
  },
  {
    "sentence_id": 21,
    "text": "现在我这个框架是写在这个是是一个非常就就是说非常广泛的这个这个这个这个这个意义下，那个所以它的应用应用的话，你看可以可以可以应用到很多的这个问题上去，那么你。",
    "language": "zh",
    "emotion": "neutral"
  },
  {
    "sentence_id": 22,
    "text": "在这个应用的时候，你也会出来很多，你也会出来很多的问题。",
    "language": "zh",
    "emotion": "neutral"
  },
  {
    "sentence_id": 23,
    "text": "怎么可能有一个这个格式，它它会有这么多的优点，它它会有这么多优点，它肯定什么地方会出来毛病。",
    "language": "zh",
    "emotion": "neutral"
  },
  {
    "sentence_id": 24,
    "text": "就是说你你我们现在证明的只是，我们现在证明的这个东西只是证明了一个这个稳定性，这个它这个解在这个修正的能量下面，它一定是稳定的，它就是稳定的。",
    "language": "zh",
    "emotion": "neutral"
  },
  {
    "sentence_id": 25,
    "text": "还没有说这个它跟这个准确解它到底是什么关系？",
    "language": "zh",
    "emotion": "neutral"
  },
  {
    "sentence_id": 26,
    "text": "稳定性不等于是收敛性，稳定性不等于说是这个解一定算出来是好。",
    "language": "zh",
    "emotion": "neutral"
  },
  {
    "sentence_id": 27,
    "text": "所以你要想把这个解算好的话，那么还得要有其他的条件，还得要其他的条件。",
    "language": "zh",
    "emotion": "neutral"
  },
  {
    "sentence_id": 28,
    "text": "那么下面我们就讲一下这个在在这个具体用的时候要要有一些什么注意事项，要有一些什么注意事项。",
    "language": "zh",
    "emotion": "neutral"
  },
  {
    "sentence_id": 29,
    "text": "那个。",
    "language": "zh",
    "emotion": "neutral"
  },
  {
    "sentence_id": 30,
    "text": "就是说你你看刚刚这个刚刚这个框架里面，我我不是说我把这个能量分成两部分嘛，对吧？",
    "language": "zh",
    "emotion": "neutral"
  },
  {
    "sentence_id": 31,
    "text": "一部分线性部分，另外一部分是剩下的。",
    "language": "zh",
    "emotion": "neutral"
  },
  {
    "sentence_id": 32,
    "text": "我这个 l 这个 l 的选取是任意的，都这个格式都都对。",
    "language": "zh",
    "emotion": "neutral"
  },
  {
    "sentence_id": 33,
    "text": "那么一个最开始的时候，那我们想的时候选取我就取 l 等于零。",
    "language": "zh",
    "emotion": "neutral"
  },
  {
    "sentence_id": 34,
    "text": "l等于零，这个这个这个格式还是显得同志对不对？",
    "language": "zh",
    "emotion": "neutral"
  },
  {
    "sentence_id": 35,
    "text": "一模一样，什么东西都没有变，你什么方程都不用解。",
    "language": "zh",
    "emotion": "neutral"
  },
  {
    "sentence_id": 36,
    "text": "就是l等于零了以后，它就是完全一个显式格式，你不用解任何方程，你可以想象这个格式会会会怎么样。",
    "language": "zh",
    "emotion": "neutral"
  },
  {
    "sentence_id": 37,
    "text": "这个格式算出来会怎么样？",
    "language": "zh",
    "emotion": "neutral"
  },
  {
    "sentence_id": 38,
    "text": "就这个格式，你可以想象，假如这个 l 取取上零的话，它这个它这个稳定性没有问题，但是你要收敛性也没有问题，就是说你还可以证明它它在有条件下面是收敛的，但是它这个收敛的意义是什么？",
    "language": "zh",
    "emotion": "neutral"
  },
  {
    "sentence_id": 39,
    "text": "是当它 t 要趋向于零的时候，它。",
    "language": "zh",
    "emotion": "neutral"
  },
  {
    "sentence_id": 40,
    "text": "它才会，它才会跟这个解比较接近。",
    "language": "zh",
    "emotion": "neutral"
  },
  {
    "sentence_id": 41,
    "text": "就是说你假如取 l 等于零的话，这个 delta t 要取得非常非常非常之小，你这个解才会跟你你想要的解它才会比较接近。",
    "language": "zh",
    "emotion": "neutral"
  },
  {
    "sentence_id": 42,
    "text": "所以 l 等于零这个不是一个好的选择，不是一个好的选择。",
    "language": "zh",
    "emotion": "neutral"
  },
  {
    "sentence_id": 43,
    "text": "你你你从原则上来讲是可以用，但是它不是一个好的选择。",
    "language": "zh",
    "emotion": "neutral"
  },
  {
    "sentence_id": 44,
    "text": "你。",
    "language": "zh",
    "emotion": "neutral"
  },
  {
    "sentence_id": 45,
    "text": "那什么样的这个 L 是一个好的选择呢？",
    "language": "zh",
    "emotion": "neutral"
  },
  {
    "sentence_id": 46,
    "text": "这个什么样的 L 是一个好的选择？",
    "language": "zh",
    "emotion": "neutral"
  },
  {
    "sentence_id": 47,
    "text": "就说这个 L ，你这个线性部分你要想办法包含你这个自由能里面最强的这个最强的那个。",
    "language": "zh",
    "emotion": "neutral"
  },
  {
    "sentence_id": 48,
    "text": "最强的这个算子，因为在很多的自由能里面都都有一个都都比较自然的有一个有一个这个有一个带导数的这个高阶的算子，那这个这个时候像这种就比较好分，你就直接这个就取L就完了，对吧？",
    "language": "zh",
    "emotion": "neutral"
  },
  {
    "sentence_id": 49,
    "text": "但是有的时候就不是很明显，或者。",
    "language": "zh",
    "emotion": "neutral"
  },
  {
    "sentence_id": 50,
    "text": "我这个明显你怎么东西取l，这个就就就就是说你有各种各样的选各种各样的选法，这就是说你做研究，做研究你你这个你你就要考虑到这种问题，对于复杂的自由能我怎么去选择，怎么去选择l，这个选选l这个就就是嗯。",
    "language": "zh",
    "emotion": "neutral"
  },
  {
    "sentence_id": 51,
    "text": "，就就是就是就是就是一个意思，就是说要要一些技巧，你怎么选这个东西，下面我就会讲一下这个怎么选L这件事情。",
    "language": "zh",
    "emotion": "neutral"
  },
  {
    "sentence_id": 52,
    "text": "另外我还忘了讲的就是说我我这。",
    "language": "zh",
    "emotion": "neutral"
  },
  {
    "sentence_id": 53,
    "text": "这这次这个课程，这个不会花什么，没有时间去讲这个空间离散。",
    "language": "zh",
    "emotion": "neutral"
  },
  {
    "sentence_id": 54,
    "text": "但是这个格式可以应用到这个所有的这个galoking，就是说这个弱形式下的这个空间离散。",
    "language": "zh",
    "emotion": "neutral"
  },
  {
    "sentence_id": 55,
    "text": "你只要你的这个，你只要你的这个方法是在弱形式下建立，那么你这个空间离散可以写成弱形式，那么这个方法都都是。",
    "language": "zh",
    "emotion": "neutral"
  },
  {
    "sentence_id": 56,
    "text": "都适用，就是完全可以照搬过去，不用不用做任何的改动，只要你的分布积分在你的空间理想下面，是满足的，那么这个这个稳定性，无条件稳定性，在这个权利长的时候还是同样满足，为什么呢？",
    "language": "zh",
    "emotion": "neutral"
  },
  {
    "sentence_id": 57,
    "text": "你看我们取的测试函数都是什么东西？",
    "language": "zh",
    "emotion": "neutral"
  },
  {
    "sentence_id": 58,
    "text": "我们取的测试函数都是谬，都是范。",
    "language": "zh",
    "emotion": "neutral"
  },
  {
    "sentence_id": 59,
    "text": "都是R对吧？",
    "language": "zh",
    "emotion": "neutral"
  },
  {
    "sentence_id": 60,
    "text": "我取的测试函数没有取复杂的测试函数，都是在你的测试空间的。",
    "language": "zh",
    "emotion": "neutral"
  },
  {
    "sentence_id": 61,
    "text": "所以你的测试函数在你的这个离散空间的话，那么你在你在这个弱形式下面，它完全这个证明完全可以搬过去。",
    "language": "zh",
    "emotion": "neutral"
  },
  {
    "sentence_id": 62,
    "text": "所以你用Galilei finite elements，用谱方法，这个。",
    "language": "zh",
    "emotion": "neutral"
  },
  {
    "sentence_id": 63,
    "text": "这个 Galerkin 方法，或者是用这个差分，差分你当然要满足这个，要满足这个 summation by parts，要要满足这个分布积分，你用这个差分有限元或者谱方法，都可以这个这个全离散，这个这个这个稳定性，我刚刚讲的这个 SIV 的这个全离散的稳定性，你同样都可以证明，全部都可以证明。",
    "language": "zh",
    "emotion": "neutral"
  },
  {
    "sentence_id": 64,
    "text": "所以这个这个不是问题，但是我我只在这里提一句，就是说我没有时间去去挨个讲这个这个空间的离散。",
    "language": "zh",
    "emotion": "neutral"
  },
  {
    "sentence_id": 65,
    "text": "那你你空间的离散，你用你自己这个比较熟悉的，你自己拿手的这个空间离散，随便随便你用哪种空间离散都行，唯一的要保证的就是说你要保证这个要保证这个分布积分是是是是是没有出错的。",
    "language": "zh",
    "emotion": "neutral"
  },
  {
    "sentence_id": 66,
    "text": "当然你把它写成弱形式就不存在分布积分的问题了。",
    "language": "zh",
    "emotion": "neutral"
  },
  {
    "sentence_id": 67,
    "text": "你你你把它写成你你好比说你你这个负拉普拉斯的这个这个phi不是这种玩意，你你这里不筛取个phi，但是你写成分布积分的形式，你就不存在，你你。",
    "language": "zh",
    "emotion": "neutral"
  },
  {
    "sentence_id": 68,
    "text": "你你写成弱形式的话，就就就无所谓，你只要你这个你只要你这个你你这个权利展示在这个弱形式下建立的，那么所有的这个这个稳定性都都可以满足，这个没有没有什么问题。",
    "language": "zh",
    "emotion": "neutral"
  },
  {
    "sentence_id": 69,
    "text": "这是一件事情，就是说空间离散不不给他造成困难的。",
    "language": "zh",
    "emotion": "neutral"
  },
  {
    "sentence_id": 70,
    "text": "第二件事情就是说，你看这个格式，这个这个格式我写了一个，我写了一个夸克尼克式，你你还可以用其他的格式对吧？",
    "language": "zh",
    "emotion": "neutral"
  },
  {
    "sentence_id": 71,
    "text": "你用 BDF 二，你用 BDF 二的话，它这个它这个稳定性是是同样没有问题的。",
    "language": "zh",
    "emotion": "neutral"
  },
  {
    "sentence_id": 72,
    "text": "你就会你会发现这个不光是用 BDF 二型，你用这个 BDF，你用三阶、四阶、五阶、六阶都可以用。",
    "language": "zh",
    "emotion": "neutral"
  },
  {
    "sentence_id": 73,
    "text": "但是这个证明就是说这个BDF三到BDF六阶的这个证明，它这个能量的证明那现在还没有，现在还没有，但是算起来是没有什么问题的。",
    "language": "zh",
    "emotion": "neutral"
  },
  {
    "sentence_id": 74,
    "text": "算起来这个基本上这个稳定性也非常好。",
    "language": "zh",
    "emotion": "neutral"
  },
  {
    "sentence_id": 75,
    "text": "所以你你的问题假如需要高阶格式的话，你也可以用高阶格式去算，你也可以用高阶格式去算，没有问题。",
    "language": "zh",
    "emotion": "neutral"
  },
  {
    "sentence_id": 76,
    "text": "但是现在证明还有还有一个这个缺口，但是但是你要不在乎这个证明的话，这个这个你要想算高阶的话，你直接就用BDF这个高阶也也没有问题。",
    "language": "zh",
    "emotion": "neutral"
  },
  {
    "sentence_id": 77,
    "text": "，另外还有什么？",
    "language": "zh",
    "emotion": "neutral"
  },
  {
    "sentence_id": 78,
    "text": "嗯。",
    "language": "zh",
    "emotion": "neutral"
  },
  {
    "sentence_id": 79,
    "text": "我要做的事情。",
    "language": "zh",
    "emotion": "sad"
  },
  {
    "sentence_id": 80,
    "text": "Achoo.",
    "language": "en",
    "emotion": "neutral"
  },
  {
    "sentence_id": 81,
    "text": "嗯。",
    "language": "zh",
    "emotion": "sad"
  },
  {
    "sentence_id": 82,
    "text": "OK，刚刚OK，刚刚讲到讲到这个地方对吧？",
    "language": "zh",
    "emotion": "neutral"
  },
  {
    "sentence_id": 83,
    "text": "就是你你这个东西只要解两次，解两次这个方程就行了，解两次这个方程就行了，然后然后这个。",
    "language": "zh",
    "emotion": "neutral"
  },
  {
    "sentence_id": 84,
    "text": "然后这这个东西就是说，在这个这两个东西都是拉普拉斯算子的情况下，还可以把它解耦成解耦成这个两个泊松方程，所以所以最后解起来的非常简单。",
    "language": "zh",
    "emotion": "neutral"
  },
  {
    "sentence_id": 85,
    "text": "那么下面我就讲一下这个要注意的这个要注意的事项。",
    "language": "zh",
    "emotion": "neutral"
  },
  {
    "sentence_id": 86,
    "text": "第一个就是就是和这个有关，就是在这个情况，就是我们做这个我。",
    "language": "zh",
    "emotion": "neutral"
  },
  {
    "sentence_id": 87,
    "text": "我我我们刚才讲的这个最主要的，现在这个最主要的就是怎么分裂，就是你有一个自由能怎么分裂。",
    "language": "zh",
    "emotion": "neutral"
  },
  {
    "sentence_id": 88,
    "text": "那么我举举这个最简单的例子，最简单例子就是这个阿兰卡和和卡基量方程，这个最常用对吧？",
    "language": "zh",
    "emotion": "neutral"
  },
  {
    "sentence_id": 89,
    "text": "最常用。",
    "language": "zh",
    "emotion": "neutral"
  },
  {
    "sentence_id": 90,
    "text": "那么这个时候，它这个 f i 这个这个 f i 前面还有一个。",
    "language": "zh",
    "emotion": "neutral"
  },
  {
    "sentence_id": 91,
    "text": "还有一个小，还有一个很大的这个常数，一除上epsilon的平方，这个epsilon是这个界面的宽度，就是对吧？",
    "language": "zh",
    "emotion": "neutral"
  },
  {
    "sentence_id": 92,
    "text": "这个这个你你，那你做做这个前面的这个这个这个系数，那这个时候。",
    "language": "zh",
    "emotion": "neutral"
  },
  {
    "sentence_id": 93,
    "text": "Thank you.",
    "language": "en",
    "emotion": "neutral"
  },
  {
    "sentence_id": 94,
    "text": "这里有没有这个很大的系数？",
    "language": "zh",
    "emotion": "neutral"
  },
  {
    "sentence_id": 95,
    "text": "这个时候你就你就这样子去，，你就你就把它自然而然的自然的这个分解成这样子的话，因为这个是自然分解，所以你这个线性这个非线性，你这样子去做的话，你就会发现呢，这个德尔塔t要取得比较小的时候，也不是非常小，就德尔塔t要取得比较小的时候，你才能算好。",
    "language": "zh",
    "emotion": "neutral"
  },
  {
    "sentence_id": 96,
    "text": "你才能算好，为什么呢？",
    "language": "zh",
    "emotion": "neutral"
  },
  {
    "sentence_id": 97,
    "text": "就是因为，就是因为，就是我们这个方法想要算好，想要算好，就是你在分解的时候，这个线性部分呢，线性部分要能对非线性部分有一个控制。",
    "language": "zh",
    "emotion": "neutral"
  },
  {
    "sentence_id": 98,
    "text": "就说你线性部分要能够控制非线性部分，但是现在这个e不数要很小的话，这个东西它它没有办法控制这个这个这个这个非线性部分。",
    "language": "zh",
    "emotion": "neutral"
  },
  {
    "sentence_id": 99,
    "text": "但是你你这个东西你可以有办法解决，那怎么解决呢？",
    "language": "zh",
    "emotion": "neutral"
  },
  {
    "sentence_id": 100,
    "text": "怎么解决？",
    "language": "zh",
    "emotion": "neutral"
  },
  {
    "sentence_id": 101,
    "text": "可不可以把他那个，把他那个关掉？",
    "language": "zh",
    "emotion": "neutral"
  },
  {
    "sentence_id": 102,
    "text": "那个锁屏时间给他关掉。",
    "language": "zh",
    "emotion": "neutral"
  },
  {
    "sentence_id": 103,
    "text": "对，是的。",
    "language": "zh",
    "emotion": "neutral"
  },
  {
    "sentence_id": 104,
    "text": "是一生中，出事了，我确实。",
    "language": "zh",
    "emotion": "sad"
  },
  {
    "sentence_id": 105,
    "text": "OK，所以，，那我们可以怎么做呢？",
    "language": "zh",
    "emotion": "neutral"
  },
  {
    "sentence_id": 106,
    "text": "可以怎么做？",
    "language": "zh",
    "emotion": "neutral"
  },
  {
    "sentence_id": 107,
    "text": "就是就是你再可以这样子，就是说我在这个里面呢，我从这个里面借一部分过来。",
    "language": "zh",
    "emotion": "neutral"
  },
  {
    "sentence_id": 108,
    "text": "因为我需要，我需要控制这个玩意儿。",
    "language": "zh",
    "emotion": "neutral"
  },
  {
    "sentence_id": 109,
    "text": "你看这里，这里面没有一除了呢，这里面没有一除上一除，所以我在这里面借一部分过来，这个 s 随便取，取一，取二都行，我借一部分，借一部分过来。",
    "language": "zh",
    "emotion": "neutral"
  },
  {
    "sentence_id": 110,
    "text": "对吧？",
    "language": "zh",
    "emotion": "neutral"
  },
  {
    "sentence_id": 111,
    "text": "这个线性线性无关，那现在我们发现这个东西不光是不光是为了这个准确性，而且是为了为了能够分解，为了能够你没有这个东西，我刚刚那个分解就出毛病了，分解要出来有虚数，a和b要虚数，你加上了这个以后就没有问题了，你加上了这个以后，你两个分解，你待会你试一下，你就发现这个分解就不用。",
    "language": "zh",
    "emotion": "neutral"
  },
  {
    "sentence_id": 112,
    "text": "不用虚数了就可以，就就就可以用这个有实数解，有实数解。",
    "language": "zh",
    "emotion": "neutral"
  },
  {
    "sentence_id": 113,
    "text": "这样子你你这个让它做线性部分，那你要保证的是什么呢？",
    "language": "zh",
    "emotion": "neutral"
  },
  {
    "sentence_id": 114,
    "text": "你减掉那个这个东西，这个东西它没有下界，对吧？",
    "language": "zh",
    "emotion": "neutral"
  },
  {
    "sentence_id": 115,
    "text": "翻负的翻的平方没有下界，但是它两个结合在一起它是有下界的，为什么有下界？",
    "language": "zh",
    "emotion": "neutral"
  },
  {
    "sentence_id": 116,
    "text": "你是f斐里面有斐的四次方，你斐的平方你负再厉害，它都斐的四次方都可能都要把它压住，所以这个下界不会错。",
    "language": "zh",
    "emotion": "neutral"
  },
  {
    "sentence_id": 117,
    "text": "你是。",
    "language": "zh",
    "emotion": "neutral"
  },
  {
    "sentence_id": 118,
    "text": "你这样子一做，它就没有毛病了，这样子一做就没有毛病了。",
    "language": "zh",
    "emotion": "neutral"
  },
  {
    "sentence_id": 119,
    "text": "你会你发现你看这个这个数字例子，就是说你在这个你你取这个时间步长非常小，好比如说10的负四次方的时候，时间步长这这两个这个这个s等于零都没有问题，就是说你加不加都算。",
    "language": "zh",
    "emotion": "neutral"
  },
  {
    "sentence_id": 120,
    "text": "都算的非常好，但是你假如时间步长一大一大的话，这个你没你这个s取零的话，s等于零的话就是没有加这个稳定一项这这项的话，它这个解就变成这个样子，它它不会它不会blow up，不会不会出界，但是它它这个算出来的这个解不是你想要的解，但是。",
    "language": "zh",
    "emotion": "neutral"
  },
  {
    "sentence_id": 121,
    "text": "但是你加上了这个，你你你取个s等于一，随便或者s等于随便等于什么东西以后，马上这个大的步长它也能算。",
    "language": "zh",
    "emotion": "neutral"
  },
  {
    "sentence_id": 122,
    "text": "就说你分解的时候，你一定要能够，一定要想办法保证你这个。",
    "language": "zh",
    "emotion": "neutral"
  },
  {
    "sentence_id": 123,
    "text": "你你这个这个，你你这个线性部分要足够强，线性部分足够强，那你这个你这个线性部分你你没有这个强的部分怎么办？",
    "language": "zh",
    "emotion": "neutral"
  },
  {
    "sentence_id": 124,
    "text": "没有强的部分你要想办法自己加，没有条件要创造条件，就是说没有没有强的时候，你就要加上这个，你就可以加上这个稳定，可以加上稳定项。",
    "language": "zh",
    "emotion": "neutral"
  },
  {
    "sentence_id": 125,
    "text": "你这个这个这个这个事情我到下面几堂课我再讲具体，具体什么样的情况可以可以加上这些，可以加上什么样的项可以可以有帮助。",
    "language": "zh",
    "emotion": "neutral"
  },
  {
    "sentence_id": 126,
    "text": "那么第二件事情，我觉得这个在这个SIV这个应用的方面，这个比较重要的事情就是就是。",
    "language": "zh",
    "emotion": "neutral"
  },
  {
    "sentence_id": 127,
    "text": "你现在可以做这个时间自适应，你现在可以做时间自适应，为什么呢？",
    "language": "zh",
    "emotion": "neutral"
  },
  {
    "sentence_id": 128,
    "text": "就是说因为你现在有无条件稳定了。",
    "language": "zh",
    "emotion": "neutral"
  },
  {
    "sentence_id": 129,
    "text": "什么叫无条件稳定？",
    "language": "zh",
    "emotion": "neutral"
  },
  {
    "sentence_id": 130,
    "text": "无条件就是你得到就随便取多大东西，但是你又希望你的解还是算得准，那你就得到题不能够乱取，对吧？",
    "language": "zh",
    "emotion": "neutral"
  },
  {
    "sentence_id": 131,
    "text": "这题不能乱取，你什么地方取大，什么地方取小，要根据你这个解的变化来来来看。",
    "language": "zh",
    "emotion": "neutral"
  },
  {
    "sentence_id": 132,
    "text": "你看这个这个自由能，这个解的这个这个一般的问题的自由能，它通常是这样子，开始的时候变化非常剧烈，然后很长的时间不怎么动，，它变化非常缓慢，，很可能在这个很久以后不怎么动，它突然又剧烈的下降一阵子，然后又很长时间不动，它这个通常的这个这个自由能的变化是这样子，所以你在这个变化非常快的时候，你时间步长取大了是肯定算不好。",
    "language": "zh",
    "emotion": "neutral"
  },
  {
    "sentence_id": 133,
    "text": "对吧？",
    "language": "zh",
    "emotion": "neutral"
  },
  {
    "sentence_id": 134,
    "text": "所以你时间步长要非常小，要要要抓住它这个变化的这个规规律。",
    "language": "zh",
    "emotion": "neutral"
  },
  {
    "sentence_id": 135,
    "text": "所以你在这个这个这些地方要取得非常小，这些地方你就可以时间步长走大。",
    "language": "zh",
    "emotion": "neutral"
  },
  {
    "sentence_id": 136,
    "text": "但是你怎么知道它什么地方大什么地方小呢？",
    "language": "zh",
    "emotion": "neutral"
  },
  {
    "sentence_id": 137,
    "text": "所以你就要用这个要要用要用这个自适应的这个时间步长。",
    "language": "zh",
    "emotion": "neutral"
  },
  {
    "sentence_id": 138,
    "text": "怎么去做自适应？",
    "language": "zh",
    "emotion": "neutral"
  },
  {
    "sentence_id": 139,
    "text": "有各种各样的办法。",
    "language": "zh",
    "emotion": "neutral"
  },
  {
    "sentence_id": 140,
    "text": "这个这个这是一个最。",
    "language": "zh",
    "emotion": "neutral"
  },
  {
    "sentence_id": 141,
    "text": "111个最直接的这个最直观的就是说你你算的这个R，我刚刚讲的这个R不是等于根号这个这个玩意儿吗？",
    "language": "zh",
    "emotion": "neutral"
  },
  {
    "sentence_id": 142,
    "text": "连续的情况下R等于这个根号这个这个能量的积分，但是但是离散的情况下这不等于它，对吧？",
    "language": "zh",
    "emotion": "neutral"
  },
  {
    "sentence_id": 143,
    "text": "离散的情况它们两个是没有关系的。",
    "language": "zh",
    "emotion": "neutral"
  },
  {
    "sentence_id": 144,
    "text": "但是可以证明，可以证明，得到这趋向于零的时候，它是收敛，它是收敛。",
    "language": "zh",
    "emotion": "neutral"
  },
  {
    "sentence_id": 145,
    "text": "所以一个这个准则就是说，你这个 R 和这个和这个原来的这个原始能量，它应该非常接近，它要不接近。",
    "language": "zh",
    "emotion": "neutral"
  },
  {
    "sentence_id": 146,
    "text": "那就说明你这个算的肯定有问题，对吧？",
    "language": "zh",
    "emotion": "neutral"
  },
  {
    "sentence_id": 147,
    "text": "那你算的肯定有问题。",
    "language": "zh",
    "emotion": "neutral"
  },
  {
    "sentence_id": 148,
    "text": "但是光这一个准则不够，光光这个能量一个一个准则还不太够，你还要加上加上一点其他的这个这个自自自适应的这个准则。",
    "language": "zh",
    "emotion": "neutral"
  },
  {
    "sentence_id": 149,
    "text": "到底具体怎么做，这个有各种办法，我们这个文章里面大概给了一种办法，也不一定是最好的办法，这个大家可以去去去试什么样的这个自适应的准则比较好一点。",
    "language": "zh",
    "emotion": "neutral"
  },
  {
    "sentence_id": 150,
    "text": "这个我这里这个图就是告诉大家，在初始的时候，你可以取你这个时间步长非常小，然后后面这个时间步长可以逐渐大到好几百倍，好几百倍，然后它还可以算的非常准。",
    "language": "zh",
    "emotion": "neutral"
  },
  {
    "sentence_id": 151,
    "text": "它可以算的非常准，但是你要开始就一直就用大步长的话，就就差的很远，算不出来。",
    "language": "zh",
    "emotion": "neutral"
  },
  {
    "sentence_id": 152,
    "text": "对，所以这个这个自适应你要做好的话，可以给你的这个这个运算量减少几10倍几百倍，可以可以可以这个可以有有有非常这个哦。",
    "language": "zh",
    "emotion": "neutral"
  },
  {
    "sentence_id": 153,
    "text": "，非常大的这个效应，非常大的事儿。",
    "language": "zh",
    "emotion": "neutral"
  },
  {
    "sentence_id": 154,
    "text": "这个是一般的格式做不到。",
    "language": "zh",
    "emotion": "neutral"
  },
  {
    "sentence_id": 155,
    "text": "你假如这个格式它有是有时间不长条件呢，有有条件稳定的，那你这个时间不长你就限制了，它就是被这个开始的这限制。",
    "language": "zh",
    "emotion": "neutral"
  },
  {
    "sentence_id": 156,
    "text": "这里这么小，你以后一直得这么小，无条件稳定的格式才能够这么做。",
    "language": "zh",
    "emotion": "neutral"
  },
  {
    "sentence_id": 157,
    "text": "所以这是。",
    "language": "zh",
    "emotion": "neutral"
  },
  {
    "sentence_id": 158,
    "text": "这是两个在用这个S A D要注意的事情，一个是怎么样分解，怎么样分解这个能量，分解的这个能量一定要一定要这个线性部分要足够强。",
    "language": "zh",
    "emotion": "neutral"
  },
  {
    "sentence_id": 159,
    "text": "第二个就是要自信，这是两件事情，我要要强调的，这里是一个这个。",
    "language": "zh",
    "emotion": "neutral"
  },
  {
    "sentence_id": 160,
    "text": "另外就是。",
    "language": "zh",
    "emotion": "neutral"
  },
  {
    "sentence_id": 161,
    "text": "就是这个，这个误差估计，这个误差估计我也没有时间讲，这个误差估计没有时间，误差估计就是技巧性的问题，就是就是技术性的问题，不是技巧性的问题，是技术性的问题。",
    "language": "zh",
    "emotion": "neutral"
  },
  {
    "sentence_id": 162,
    "text": "就是说你有了这个能量估计以后，原来就是说大家对这个方向这个有一点了解的话就会知道，原来对这些很多格式做这个误差分析的时候，它都要求都要求这个就是我们昨天讲的所谓的这个李普希茨条件，都是要求这个要求这个f两撇的这个发这个东西这个无穷模要小于等于一个常数，那就这个条件。",
    "language": "zh",
    "emotion": "neutral"
  },
  {
    "sentence_id": 163,
    "text": "这个条件我刚才昨天讲的这个即使是双解模式都不满足，所以。",
    "language": "zh",
    "emotion": "neutral"
  },
  {
    "sentence_id": 164,
    "text": "所以你要求了这个条件，那个做出的这个误差分析就是不完美，不不不不好看。",
    "language": "zh",
    "emotion": "neutral"
  },
  {
    "sentence_id": 165,
    "text": "那么对于这种S M V方法，你就不需要加这种条件。",
    "language": "zh",
    "emotion": "neutral"
  },
  {
    "sentence_id": 166,
    "text": "为什么不需要加这种条件？",
    "language": "zh",
    "emotion": "neutral"
  },
  {
    "sentence_id": 167,
    "text": "它加这种条件是想证明这个格式的稳定性，它这有了这个条件它才有稳定性，有了稳定性才有收敛性。",
    "language": "zh",
    "emotion": "neutral"
  },
  {
    "sentence_id": 168,
    "text": "那我们现在没有这个条件我就有稳定性，所以我就收敛性分析的时候我就不需要这个条件。",
    "language": "zh",
    "emotion": "neutral"
  },
  {
    "sentence_id": 169,
    "text": "这个收敛性不不不需要这个，所以这个是，这个是一个这个这个S A B的一个大的优点，就是你可以做这个收敛性分析。",
    "language": "zh",
    "emotion": "neutral"
  },
  {
    "sentence_id": 170,
    "text": "现在这个收敛性分析，，在这个半离散有限元或者有限差分的这个我们都都都做了一些，这都是都是技巧性的问题，或都是技术性的问题，没有本质上的，没有太多这个本质上的困难。",
    "language": "zh",
    "emotion": "neutral"
  },
  {
    "sentence_id": 171,
    "text": "就是说你给一个不同的自由能，你都可以，你只要有技术上你你掌握了这个掌握了这个分析的这个这些技术的话，你都可以证明它的这个这个格式的这个收敛性都不是都不是太大的这个问题。",
    "language": "zh",
    "emotion": "neutral"
  },
  {
    "sentence_id": 172,
    "text": "，那下面我就讲一下这个这个一些推广，一些一些一一些推广。",
    "language": "zh",
    "emotion": "neutral"
  },
  {
    "sentence_id": 173,
    "text": "那么这个第一个这个推广呢，自然的就是这个。",
    "language": "zh",
    "emotion": "neutral"
  },
  {
    "sentence_id": 174,
    "text": "，这里面我我讲的时候，这个斐，这个这个斐不一定是，虽然这里是是单个变，这这里写的是这个斐是是一个一个这个标量函数，但是这个斐可以是向量函数，斐。",
    "language": "zh",
    "emotion": "neutral"
  },
  {
    "sentence_id": 175,
    "text": "可以是向量函数，就是说它可以是很多个这个这个位置量，可以是很多个函数，可以是向量，不一定是标量。",
    "language": "zh",
    "emotion": "neutral"
  },
  {
    "sentence_id": 176,
    "text": "这个尤其这个东西，尤其是在做材料的时候非常重要，因为材料的时候它的这个这个位置量，唯一这个这个order point不是一个，经常是几个、几10个，甚至几百个，这个这个这个这个这个三一、三二、333很多。",
    "language": "zh",
    "emotion": "neutral"
  },
  {
    "sentence_id": 177,
    "text": "这个这个时候你你怎么构造这个格式？",
    "language": "zh",
    "emotion": "neutral"
  },
  {
    "sentence_id": 178,
    "text": "这个时候这个SV这个格式构造起来同样的简单，是一回事情。",
    "language": "zh",
    "emotion": "neutral"
  },
  {
    "sentence_id": 179,
    "text": "你好比说从这个自由能出发，是吧？",
    "language": "zh",
    "emotion": "neutral"
  },
  {
    "sentence_id": 180,
    "text": "自由能出发，它一般的情况下它都有它这个它这个在材料力学或者其他的这个这个它一般情况下也都有一个线性部分，这个线性部分这个有可能通常是。",
    "language": "zh",
    "emotion": "neutral"
  },
  {
    "sentence_id": 181,
    "text": "是，是这个不同的这个不同的这个分量是没有关系的，有关系没有关系，那个我现在简单的取件就是说它这个是这个是这个没有l i j，只有l i就行。",
    "language": "zh",
    "emotion": "neutral"
  },
  {
    "sentence_id": 182,
    "text": "这个分一下，包括在都都假设在这个里头，假设在这个里头，这个就是已经积分过了，这这都是这个这都是内积，这都是已经积分了，这个这个因为是能量嘛，能量都是都是已经积分了。",
    "language": "zh",
    "emotion": "neutral"
  },
  {
    "sentence_id": 183,
    "text": "那么不管你有多少个分量，不管你有多少个分量，你只要引进一个这个，你只要引进一个S A V就行。",
    "language": "zh",
    "emotion": "neutral"
  },
  {
    "sentence_id": 184,
    "text": "你只要引进一个S A V，就是S A V就等于这个这一部分，这个非线性的这个部分，假设它有下界，然后。",
    "language": "zh",
    "emotion": "neutral"
  },
  {
    "sentence_id": 185,
    "text": "它的这个方程，它的这个梯度流，对这个的梯度流是什么东西呢？",
    "language": "zh",
    "emotion": "neutral"
  },
  {
    "sentence_id": 186,
    "text": "对这个梯度流，假如我这个 g 是取这个东西呢，g 是取负拉普拉斯了，就是呢，对这个东西，对每一个分量，对 t 求导，那么，这个 nu i 就是就是对对。",
    "language": "zh",
    "emotion": "neutral"
  },
  {
    "sentence_id": 187,
    "text": "对这个对这个东西对斐i的这个变分导数，对斐i的变分导数，你看，对这个求对斐i求变分导数，这里出来就是线性部分就是这个嘛，非线性部分这个东西对斐i求变分导数，就是这个东西对斐i求变分导数，对吧？",
    "language": "zh",
    "emotion": "neutral"
  },
  {
    "sentence_id": 188,
    "text": "对吧？",
    "language": "zh",
    "emotion": "neutral"
  },
  {
    "sentence_id": 189,
    "text": "然后这个r你对t求导，同样的出来，这个对t求导，那就说对每一个变量它都对t有关系，所以这里面说的是对每一个变量，然后求这个变分导数，然后对每一个变量对t求导数，然后你把它加起来积分，就出来是这个。",
    "language": "zh",
    "emotion": "neutral"
  },
  {
    "sentence_id": 190,
    "text": "这是这是多个函数的这个梯度流，就是就是就是写成这个形形状。",
    "language": "zh",
    "emotion": "neutral"
  },
  {
    "sentence_id": 191,
    "text": "那么这个时候你做这个S A B，你同样的做对吧？",
    "language": "zh",
    "emotion": "neutral"
  },
  {
    "sentence_id": 192,
    "text": "你同样的做，这里还是用克拉克尼克斯举例子，同样的做，这个线性部分显示，非线性部分隐示，非部分隐示，这里这个跟刚刚一模一样的做，跟刚刚一模一样。",
    "language": "zh",
    "emotion": "neutral"
  },
  {
    "sentence_id": 193,
    "text": "它所有的东西都耦合在一起，耦合在一起，但是都什么都都是被什么东西耦合，就是被这么一个数，被这个 r n 加一就是一个数，就被 r n 加一个数耦合。",
    "language": "zh",
    "emotion": "neutral"
  },
  {
    "sentence_id": 194,
    "text": "你要把这个大矩阵写出来，它是个什么样子？",
    "language": "zh",
    "emotion": "neutral"
  },
  {
    "sentence_id": 195,
    "text": "它这个东西是耦合的，但是你把这个大矩阵写出来。",
    "language": "zh",
    "emotion": "neutral"
  },
  {
    "sentence_id": 196,
    "text": "你把这个大矩阵写出来，它这这里就是，这里就是阿尔法一 i 这个 l i，这个 l 一，这个这个阿尔法二 i l 二，这个阿尔法三 i l 三，，然后，然后。",
    "language": "zh",
    "emotion": "neutral"
  },
  {
    "sentence_id": 197,
    "text": "就是就是然后然后这里是一个常数，然后这里是这个，这里是这里是斐一，斐二，斐k，然后这里就是r n加一，n加一，n加一，这一个短项对吧？",
    "language": "zh",
    "emotion": "neutral"
  },
  {
    "sentence_id": 198,
    "text": "这个右端项，这个这个大的矩阵就是这样子。",
    "language": "zh",
    "emotion": "neutral"
  },
  {
    "sentence_id": 199,
    "text": "然后这里是，这里是一些非线性项，你不管它，对吧？",
    "language": "zh",
    "emotion": "neutral"
  },
  {
    "sentence_id": 200,
    "text": "就这些你不管它，只被这一个，只被这一个东西所这个所包耦合在一起。",
    "language": "zh",
    "emotion": "neutral"
  },
  {
    "sentence_id": 201,
    "text": "那么你你想怎么减呢？",
    "language": "zh",
    "emotion": "neutral"
  },
  {
    "sentence_id": 202,
    "text": "这个减跟刚刚一样，你这个东西叫一个。",
    "language": "zh",
    "emotion": "neutral"
  },
  {
    "sentence_id": 203,
    "text": "这个是一个大矩阵，你对这个大矩阵，你做做这个做这个块状的高斯消去，你就把这个R算出来。",
    "language": "zh",
    "emotion": "neutral"
  },
  {
    "sentence_id": 204,
    "text": "算这个R的时候，你要求这个的逆，要求这个逆，求这个的逆，你会发现这个逆是什么？",
    "language": "zh",
    "emotion": "neutral"
  },
  {
    "sentence_id": 205,
    "text": "这个逆它是解耦的，它每一个都是分开的。",
    "language": "zh",
    "emotion": "neutral"
  },
  {
    "sentence_id": 206,
    "text": "所以每一个都是分开的，你解这个力的时候，你只要把这个方程解一遍，对每一个分量解一遍，，它完全解好，对每一个分量解一遍，你就把这个r算出来，你r算出来把它移到右边去，再把这个东西解一遍，你就把所有的东西都算出来，所以这个格式。",
    "language": "zh",
    "emotion": "neutral"
  },
  {
    "sentence_id": 207,
    "text": "就是说对于不管你有多少个分量，不管你有多少个分量，它都只要算这个解偶的常系数的这个这个方程，解偶的常系数的方程，不管它有多少多少玩意都都都都可以。",
    "language": "zh",
    "emotion": "neutral"
  },
  {
    "sentence_id": 208,
    "text": "所以这第一个这个这个推广，就是就是我想给大家这个特别强调的就是说，你有多个分量，你有多个分量的这个方系统的话，那么你也可以只要不用很多的这个ACD，只要一个ACD就搞定了。",
    "language": "zh",
    "emotion": "neutral"
  },
  {
    "sentence_id": 209,
    "text": "然后所需要解的话就是每一步你只要解一个这个。",
    "language": "zh",
    "emotion": "neutral"
  },
  {
    "sentence_id": 210,
    "text": "每一步你只要解一个这个这个就行。",
    "language": "zh",
    "emotion": "neutral"
  },
  {
    "sentence_id": 211,
    "text": "那么这个事情就是就是说我跟这个我跟我一个这个长期这个材料力学里面的合合作者这个正在做这件事情，就是他以前呢，他他们经常做这个材料这个模拟，都是几百种，有有有几百个这个order parameter在这里头，他以前就就很麻烦，他要么他就是显示的解，这个时间步长非常小，要么这个耦合在一起他也解不动，耦合在一起，因为这个方程组全部是耦合在一起，他解不动。",
    "language": "zh",
    "emotion": "neutral"
  },
  {
    "sentence_id": 212,
    "text": "那现在这样子这样子了以后，一下把他的这个程序可以增加的这个速度增加几千倍，就是说就是说这个因为我只要每一步我这解这个解耦的方式走，而且时间步长可以取得非常大，对吧？",
    "language": "zh",
    "emotion": "neutral"
  },
  {
    "sentence_id": 213,
    "text": "那步长可以取得非常大，所以这个用好可以这个效率可以大大增加。",
    "language": "zh",
    "emotion": "neutral"
  },
  {
    "sentence_id": 214,
    "text": "这是第一件事情。",
    "language": "zh",
    "emotion": "neutral"
  },
  {
    "sentence_id": 215,
    "text": "那么第二件事情，我给大家举个例子，就是假如你你你这个东西，这个非渐进项它没有下界怎么办？",
    "language": "zh",
    "emotion": "neutral"
  },
  {
    "sentence_id": 216,
    "text": "非渐进那一部分没有下界怎么办？",
    "language": "zh",
    "emotion": "neutral"
  },
  {
    "sentence_id": 217,
    "text": "整个的能量它是一定有下界的。",
    "language": "zh",
    "emotion": "neutral"
  },
  {
    "sentence_id": 218,
    "text": "对吧？",
    "language": "zh",
    "emotion": "neutral"
  },
  {
    "sentence_id": 219,
    "text": "整个的能量它是一定有下界，因为整个能量要没有下界，那那你怎么去做它的这个 minimum 这些，这这不可能做梯度就是没有意义的。",
    "language": "zh",
    "emotion": "neutral"
  },
  {
    "sentence_id": 220,
    "text": "所以整个能量一定有下界，但是你这个有的时候你这个非线性项没有下界，你你那你就得想点办法。",
    "language": "zh",
    "emotion": "neutral"
  },
  {
    "sentence_id": 221,
    "text": "你好比说这个做薄膜增长的这个一个模型，它的这个自由能就是就是这样子。",
    "language": "zh",
    "emotion": "neutral"
  },
  {
    "sentence_id": 222,
    "text": "它的自由度就是个，就是这个log在这里。",
    "language": "zh",
    "emotion": "neutral"
  },
  {
    "sentence_id": 223,
    "text": "你你看它这种情况，你好像自然而然的，我自然而然的这个分解就是说，这是我的线性部分，这是我的非线性部分，对不对？",
    "language": "zh",
    "emotion": "neutral"
  },
  {
    "sentence_id": 224,
    "text": "但是问题是现在这个非线性这部分它没有下界。",
    "language": "zh",
    "emotion": "neutral"
  },
  {
    "sentence_id": 225,
    "text": "它它它没有下界，没有下界，就是说你就你就你就没有办法，你就没有办法用了，你就没有办法用了。",
    "language": "zh",
    "emotion": "neutral"
  },
  {
    "sentence_id": 226,
    "text": "但是我们知道它的整整个能量是一定是有下界的，所以你要做一点这个数学上的分析，你要做点数学上的分析，你可以你可以这个。",
    "language": "zh",
    "emotion": "neutral"
  },
  {
    "sentence_id": 227,
    "text": "你看这里是一个常数，就会你就会发现，这个自己它的积分没有下界，但是你只要从这里面，从这个线性里面借一点过来，借一点过来就行，这这个阿尔法大于零，任意的阿尔法大于零，只要借一点过来，你就可以证明它这个积分是有下界的。",
    "language": "zh",
    "emotion": "neutral"
  },
  {
    "sentence_id": 228,
    "text": "因为因为这个东西比这个东西强多了，这个这个拉普拉斯算子平方比这个log这个东西强多了，所以所以它这个东西可能有有下界。",
    "language": "zh",
    "emotion": "neutral"
  },
  {
    "sentence_id": 229,
    "text": "那么有下界就是说你分解的时候，那你要怎么分解呢？",
    "language": "zh",
    "emotion": "neutral"
  },
  {
    "sentence_id": 230,
    "text": "你就是说你要这里面要给出一部分给它，，就是说这个当做你的这个第二部分，那么这个是你的线性部分，这个是线性。",
    "language": "zh",
    "emotion": "neutral"
  },
  {
    "sentence_id": 231,
    "text": "这样子的话，你的分，这这就是这个分解的时候要注意，就是说你要保证第二部分要有下界。",
    "language": "zh",
    "emotion": "neutral"
  },
  {
    "sentence_id": 232,
    "text": "那你这样子的话，你就你就可以，你下面就可以用这个S A V去做了，就就不会有任何的麻烦，对吧？，",
    "language": "zh",
    "emotion": "neutral"
  },
  {
    "sentence_id": 233,
    "text": "就可以用这个S A V去做。",
    "language": "zh",
    "emotion": "neutral"
  },
  {
    "sentence_id": 234,
    "text": "所以这是这是一个这个例子，就是说假如我这个非线性里面有没有下界的部分怎么办？",
    "language": "zh",
    "emotion": "neutral"
  },
  {
    "sentence_id": 235,
    "text": "有没有下界的部分，那你就得想办法要从这个线性部分里面借一点过来，然后想办法证明它它借了一部分过来以后，它那部分有下界，然后就可以继续用。",
    "language": "zh",
    "emotion": "neutral"
  },
  {
    "sentence_id": 236,
    "text": "所以这是，，剩下的都，这个好处，这个S C P方法就是好处，它是一个菜单式，就是说你只要把这个分裂搞定了，剩下的我就不用写了，剩下的每次都是一样的，所以我这项目就就就就过了，我就不写，就不给他们讲，就是每一次都是一样的，因为你有了分裂以后，我这个就是一个菜单，就是你照照照照模照照着这个菜单做就可以。",
    "language": "zh",
    "emotion": "neutral"
  },
  {
    "sentence_id": 237,
    "text": "那么再下面一个一个例子就是说我我现在给大家讲就是说这个东西你可以往哪哪方面推广，对吧？",
    "language": "zh",
    "emotion": "neutral"
  },
  {
    "sentence_id": 238,
    "text": "在下面这个例子就是。",
    "language": "zh",
    "emotion": "neutral"
  },
  {
    "sentence_id": 239,
    "text": "就说我假如我这个梯度流是有这个是有限制的，那怎么办？",
    "language": "zh",
    "emotion": "neutral"
  },
  {
    "sentence_id": 240,
    "text": "因为我有些自自由能，我自由能是我给这个梯度流，但是不是光光这个梯度流，我还需要满足一些其他的性质，好比说什么质量守恒，面积守恒，体积守恒这些玩意。",
    "language": "zh",
    "emotion": "neutral"
  },
  {
    "sentence_id": 241,
    "text": "这个在做这个材料力学的时候经常经常要要，就是说你你你描述一个东西，它它材料进去，它它既然要保持体积守恒呢，或者要保持这个膜守恒呢，或者要保持这个表面积守恒呢，这个这个东西你怎么做？",
    "language": "zh",
    "emotion": "neutral"
  },
  {
    "sentence_id": 242,
    "text": "那么这个东西就是说我在这个在我这个方程里面。",
    "language": "zh",
    "emotion": "neutral"
  },
  {
    "sentence_id": 243,
    "text": "在我这个这个这个方程里面就就没有描没有描述这件事情，对吧？",
    "language": "zh",
    "emotion": "neutral"
  },
  {
    "sentence_id": 244,
    "text": "我我不是说我们这个方程都是写成这种形式的，都是这种形式，但是这种形式里面，我我怎么加限制，就是我这个这个限制怎么弄？",
    "language": "zh",
    "emotion": "neutral"
  },
  {
    "sentence_id": 245,
    "text": "那么我这里给大家举个例子。",
    "language": "zh",
    "emotion": "neutral"
  },
  {
    "sentence_id": 246,
    "text": "，你好比说，我考虑这个，这个这个一个这种包囊包囊的这种生物生物医学里的这个这种包囊的生长模型，包囊生长模型就是说它这个包囊这个。",
    "language": "zh",
    "emotion": "neutral"
  },
  {
    "sentence_id": 247,
    "text": "这个包囊的这个体积，在这个演变的过程是保持不变的，而且它的这个表面面积也是不变的。",
    "language": "zh",
    "emotion": "neutral"
  },
  {
    "sentence_id": 248,
    "text": "就是说这边一变它是不对的，它是它这个生长过程，它要满足这么一个表面面积和一个体积不变，那么它的自由能是什么？",
    "language": "zh",
    "emotion": "neutral"
  },
  {
    "sentence_id": 249,
    "text": "它的自由能是这种。",
    "language": "zh",
    "emotion": "neutral"
  },
  {
    "sentence_id": 250,
    "text": "是是由这个 bending 自由能给给出来的，就是取这样这个形式，取这样这个形式，这个这个就比较复杂了。",
    "language": "zh",
    "emotion": "neutral"
  },
  {
    "sentence_id": 251,
    "text": "这里这个 g，这里这个 f 是这个双井势能，这个 g 是 f 的一撇，然后加上一个负拉普拉斯，然后整个再求平方，就是就是就比较复杂一个自由能。",
    "language": "zh",
    "emotion": "neutral"
  },
  {
    "sentence_id": 252,
    "text": "比较复杂一个自由能，如果它的体积，体积因为斐等于一，好比说斐等于一就是就是这个包囊，斐等于负一就是就是边上的这个水。，",
    "language": "zh",
    "emotion": "neutral"
  },
  {
    "sentence_id": 253,
    "text": "所以这个它的这个包囊这个体积就是斐加一除上1/2的这个积分，这是体积。",
    "language": "zh",
    "emotion": "neutral"
  },
  {
    "sentence_id": 254,
    "text": "那它这个表面积，这个表面积就是有一个公式，这个有一个公式，有个逼近公式，它这个表面积的这个逼近公式就是就是这样子，就跟我们这个跟这个自由能很像，就是就是这个表面积的这个公式。",
    "language": "zh",
    "emotion": "neutral"
  },
  {
    "sentence_id": 255,
    "text": "这个表面积要在这个演化的过程中也要保持。",
    "language": "zh",
    "emotion": "neutral"
  },
  {
    "sentence_id": 256,
    "text": "那么那么你怎么你你怎么达到怎么做这件事情，怎么做这件事情，我们知道要要有这个。",
    "language": "zh",
    "emotion": "neutral"
  },
  {
    "sentence_id": 257,
    "text": "，有两种办法做这种事情。",
    "language": "zh",
    "emotion": "neutral"
  },
  {
    "sentence_id": 258,
    "text": "一个办法就是你引进拉格朗日乘子，使得它满足满足这个限制。",
    "language": "zh",
    "emotion": "neutral"
  },
  {
    "sentence_id": 259,
    "text": "那引进拉格朗日乘子满足这个限制，那就那就跳出了这个框架。",
    "language": "zh",
    "emotion": "neutral"
  },
  {
    "sentence_id": 260,
    "text": "那这个框架也可以做，只是比较麻烦一点，跳出这个框架。",
    "language": "zh",
    "emotion": "neutral"
  },
  {
    "sentence_id": 261,
    "text": "那现在我想还想用这个框架的话，那我可以怎么做呢？",
    "language": "zh",
    "emotion": "neutral"
  },
  {
    "sentence_id": 262,
    "text": "我可以加上这个惩，我用这个惩罚。",
    "language": "zh",
    "emotion": "neutral"
  },
  {
    "sentence_id": 263,
    "text": "把惩罚方法又什么意思呢？",
    "language": "zh",
    "emotion": "neutral"
  },
  {
    "sentence_id": 264,
    "text": "我在这个自由能里面，我在原来的自由能里面加上两个惩罚项，加上两个惩罚项，你看，这是初始表面积，，这是初始体积，这是初始表面积，我让它们的差。",
    "language": "zh",
    "emotion": "neutral"
  },
  {
    "sentence_id": 265,
    "text": "在这个能量里加上，把它能量差加上，加加到能量里去，然后这里是伽马和艾塔是两个小参数，是两个小参数，我参数取的足够小，因为它能量要你你在这个演化的时候能量要下降，所以这个能量要下降的话，那么这个A翻一定。",
    "language": "zh",
    "emotion": "neutral"
  },
  {
    "sentence_id": 266,
    "text": "你伽马取的足够小，a方就等于阿尔法，b方就大致等于贝塔，所以它一定是这样子，对吧？",
    "language": "zh",
    "emotion": "neutral"
  },
  {
    "sentence_id": 267,
    "text": "一定是就可以就可以这个保持，，哦，就就可以保持这个体积和保持这个表面积。",
    "language": "zh",
    "emotion": "neutral"
  },
  {
    "sentence_id": 268,
    "text": "那那你就去考虑这个能量就行了，是吧？",
    "language": "zh",
    "emotion": "neutral"
  },
  {
    "sentence_id": 269,
    "text": "你就你就不对原来这个能量去做这个做这个变分，做这个梯度流，你现在对这个能量去做梯度流，那原则上来讲，你就可以用了，你就S A D就可以用了，对吧？",
    "language": "zh",
    "emotion": "neutral"
  },
  {
    "sentence_id": 270,
    "text": "那这个就直接就可以用上去。",
    "language": "zh",
    "emotion": "neutral"
  },
  {
    "sentence_id": 271,
    "text": "但是我们这个开始就是就就直接这么做，就直接用一个S A D，，那刚刚那个菜谱你完全就直接可以用上去，没问题。",
    "language": "zh",
    "emotion": "neutral"
  },
  {
    "sentence_id": 272,
    "text": "但是发现就是在用的时候，你。",
    "language": "zh",
    "emotion": "neutral"
  },
  {
    "sentence_id": 273,
    "text": "你要这个时间步长要要非常小才行，对不对？",
    "language": "zh",
    "emotion": "neutral"
  },
  {
    "sentence_id": 274,
    "text": "非常小才行。",
    "language": "zh",
    "emotion": "neutral"
  },
  {
    "sentence_id": 275,
    "text": "这个毛病在什么地方呢？",
    "language": "zh",
    "emotion": "neutral"
  },
  {
    "sentence_id": 276,
    "text": "毛病就是说你看，我这个这个里面有一个小参数，有一个 epsilon，它是代表这个薄膜薄膜的那个界面的这个宽度。",
    "language": "zh",
    "emotion": "neutral"
  },
  {
    "sentence_id": 277,
    "text": "这里面又有两个小参数，伽马、a 呗，是是想想要这个保持这个保持这两个东西守恒的这个小参数。",
    "language": "zh",
    "emotion": "neutral"
  },
  {
    "sentence_id": 278,
    "text": "所以这三个小参数搞在一起，就使得这个使得我随便怎么分裂，它的。",
    "language": "zh",
    "emotion": "neutral"
  },
  {
    "sentence_id": 279,
    "text": "它的这个非线性项都都非常强，我没有办法搞定，就是说一个这个SIV，就是说没有办法这个很好的这个这个处理这个它的这个刚性，就这个非线性的刚性，没办法很好处理。",
    "language": "zh",
    "emotion": "neutral"
  },
  {
    "sentence_id": 280,
    "text": "所以就是说这个时候，也就是说一个这个解决的办法就是说你对于。",
    "language": "zh",
    "emotion": "neutral"
  },
  {
    "sentence_id": 281,
    "text": "对于每一个这个小参数，你要要引进一个SIV来处理它的这个刚性，因为这样子的话，我就可以引进适当的这个，，我就可以适当的这个调节这个这个这个分解，使得这个。",
    "language": "zh",
    "emotion": "neutral"
  },
  {
    "sentence_id": 282,
    "text": "使得使得使得它可以算的，它它的刚性减弱。",
    "language": "zh",
    "emotion": "neutral"
  },
  {
    "sentence_id": 283,
    "text": "那么具体做法是怎么做呢？",
    "language": "zh",
    "emotion": "neutral"
  },
  {
    "sentence_id": 284,
    "text": "具体做法呢，就是就是这样子，这个就是我对于这个，我对于这个表面表面面积。",
    "language": "zh",
    "emotion": "neutral"
  },
  {
    "sentence_id": 285,
    "text": "，我引进一个S A V的变量叫u，这个这是一个S A V。",
    "language": "zh",
    "emotion": "neutral"
  },
  {
    "sentence_id": 286,
    "text": "本来我应该对于这个体积，我也应该引进一个S A V，但是但是这个体积这一项，体积是一个线性。",
    "language": "zh",
    "emotion": "neutral"
  },
  {
    "sentence_id": 287,
    "text": "体积是一个是一个线性的这个东西，所以这个体积这一项我可以，我可以这个放到放到这个线性部分里面去，所以我就就省了一个S A B了。",
    "language": "zh",
    "emotion": "neutral"
  },
  {
    "sentence_id": 288,
    "text": "我为什么要省个S A B？",
    "language": "zh",
    "emotion": "neutral"
  },
  {
    "sentence_id": 289,
    "text": "待会给大家说。",
    "language": "zh",
    "emotion": "neutral"
  },
  {
    "sentence_id": 290,
    "text": "这里你也可以对这个体积引进一个S A B，那这个体积我就把它放到线性里头去。",
    "language": "zh",
    "emotion": "neutral"
  },
  {
    "sentence_id": 291,
    "text": "然后我要把这个展开，对不对？",
    "language": "zh",
    "emotion": "neutral"
  },
  {
    "sentence_id": 292,
    "text": "我要把这个主要的线性项给它找出来，我把这个东西两个展开。",
    "language": "zh",
    "emotion": "neutral"
  },
  {
    "sentence_id": 293,
    "text": "展开，n d energy 是等于负的拉普拉斯方，这个加上这个加加加上这个积分，这里有什么 epsilon 我就先不管它，这 epsilon 在哪里？",
    "language": "zh",
    "emotion": "neutral"
  },
  {
    "sentence_id": 294,
    "text": "这里有个什么，这个一不用先不管它，我就反正就是这样子。",
    "language": "zh",
    "emotion": "neutral"
  },
  {
    "sentence_id": 295,
    "text": "那么你把它展开对吧？",
    "language": "zh",
    "emotion": "neutral"
  },
  {
    "sentence_id": 296,
    "text": "展开这里是负拉普拉斯斐的平方，，加上这个，，减上这个两倍的这个积分拉普拉斯斐，然后加上这个积分的平方，对吧？",
    "language": "zh",
    "emotion": "neutral"
  },
  {
    "sentence_id": 297,
    "text": "这个嘛，所以所以这个是显然就是你想要的这个线性项，那这个东西就是就是你的这个非线性项，，这是你的非线性项，所以你做的时候。",
    "language": "zh",
    "emotion": "neutral"
  },
  {
    "sentence_id": 298,
    "text": "你做的时候，你你就这个。",
    "language": "zh",
    "emotion": "neutral"
  },
  {
    "sentence_id": 299,
    "text": "你对这个非线性项，这里这里这个非线性项，这个这个玩意儿，这个非线性项，这里这是这是两个非线性项，它它显然是正的，它显然是正的，所以你随便取个常数就完了。",
    "language": "zh",
    "emotion": "neutral"
  },
  {
    "sentence_id": 300,
    "text": "然后引进另一个s n v，就是两个s n v，我这里为什么没有根号呢？",
    "language": "zh",
    "emotion": "neutral"
  },
  {
    "sentence_id": 301,
    "text": "这里为什么没有根号呢？",
    "language": "zh",
    "emotion": "neutral"
  },
  {
    "sentence_id": 302,
    "text": "这个我本来就是平方，所以就是你你要写上根号也可以，写上根号这个东西的平方是吧？",
    "language": "zh",
    "emotion": "neutral"
  },
  {
    "sentence_id": 303,
    "text": "都都是都是根号的平方一样的，所以我引进两个这个s v，那么那我就把原来的这个能量。",
    "language": "zh",
    "emotion": "neutral"
  },
  {
    "sentence_id": 304,
    "text": "我给它用这两个s a v改写出来，那这个线性项我就放在这里，然后这个东西也是线性项，所以这都是我的线性项。，",
    "language": "zh",
    "emotion": "neutral"
  },
  {
    "sentence_id": 305,
    "text": "这个非线性项就由非线性项就就就用这两个s a v来表示，，非线性项就用两个s a v来表示。",
    "language": "zh",
    "emotion": "neutral"
  },
  {
    "sentence_id": 306,
    "text": "那下面我的梯度流，我的梯度流我就可以用这两个a c b来来改写，两个a c b来改写，这个时候这个g，我这里这个g就是，我这个g就是这个就是就是一个这个某b的值，就是一个常数，或者我这个g就是一个常数，某b的值。",
    "language": "zh",
    "emotion": "neutral"
  },
  {
    "sentence_id": 307,
    "text": "那个那个常数，然后这个缪就是它的变分，对这个这个这个这这个能量的这个变分导数，变分变分导数呢就一个个求，这个求求出来是这个，这个求出来是这个，这个求出来是这个，那么对这个变分导数，那么就是u，对吧，这个我就不写出来了，就就直接写德尔塔u德尔塔v就完了，对v德尔塔v的导分，然后你要两个u和v的这个对t。",
    "language": "zh",
    "emotion": "neutral"
  },
  {
    "sentence_id": 308,
    "text": "对t求导数，它就得出这样子两个这个非局部的这个方程，所以这个就是我的梯度流。",
    "language": "zh",
    "emotion": "neutral"
  },
  {
    "sentence_id": 309,
    "text": "那你有了这个以后，下面呢下面呢又都是蔡五化了，又又都是跟原来一样的，跟跟原来一样的格式，你原来是只有一个s，你现在有两个s，也是一回事情。",
    "language": "zh",
    "emotion": "neutral"
  },
  {
    "sentence_id": 310,
    "text": "准则是一样，线性部分隐式，非线性部分这个这个这个变分导数这都是非线性部分显式，一模一样。，",
    "language": "zh",
    "emotion": "neutral"
  },
  {
    "sentence_id": 311,
    "text": "非线性部分显式，线性部分隐式。",
    "language": "zh",
    "emotion": "neutral"
  },
  {
    "sentence_id": 312,
    "text": "这个还是按原来的菜这么做，那么这个这个东西还是外插。",
    "language": "zh",
    "emotion": "neutral"
  },
  {
    "sentence_id": 313,
    "text": "所以这样子还是得出一个线性二阶无条件稳定格式没有问题，，线性二阶无条件稳定格式。",
    "language": "zh",
    "emotion": "neutral"
  },
  {
    "sentence_id": 314,
    "text": "那么这个时候，，你要去解它，它这个是解耦的，但是这个解耦现在现在它的这个跟原来这个东西不太一样，，现在是什么呢？",
    "language": "zh",
    "emotion": "neutral"
  },
  {
    "sentence_id": 315,
    "text": "就是你把它这个，你把它写成一个大的这个方程组，它就是这样的，它是这个斐、谬、这个u、v，对吧？",
    "language": "zh",
    "emotion": "neutral"
  },
  {
    "sentence_id": 316,
    "text": "斐n加，谬n加。",
    "language": "zh",
    "emotion": "neutral"
  },
  {
    "sentence_id": 317,
    "text": "u n减 v n减，你把这两个可以可以搞在一起，把这两个搞在一起。",
    "language": "zh",
    "emotion": "neutral"
  },
  {
    "sentence_id": 318,
    "text": "那么这里还是跟原来一样是常系数，这里还是跟原来是一样是常系数。",
    "language": "zh",
    "emotion": "neutral"
  },
  {
    "sentence_id": 319,
    "text": "好，这里是这个什么什么什么什么什么什么什么什么什么什么什么什么什么什么什么什么什么什么什么什么",
    "language": "zh",
    "emotion": "neutral"
  },
  {
    "sentence_id": 320,
    "text": "这里是是是是什么东西？",
    "language": "zh",
    "emotion": "neutral"
  },
  {
    "sentence_id": 321,
    "text": "这里是两个对角阵，这是是一个对角阵，a b，这是就它的就是就是一个这样子的玩意，对吧？",
    "language": "zh",
    "emotion": "neutral"
  },
  {
    "sentence_id": 322,
    "text": "就是个这样子的，然后。",
    "language": "zh",
    "emotion": "neutral"
  },
  {
    "sentence_id": 323,
    "text": "然后这个矩阵你还把它叫做A，所以你算的时候，你还是你你算的时候你还是要干什么？",
    "language": "zh",
    "emotion": "neutral"
  },
  {
    "sentence_id": 324,
    "text": "算的时候你还是这里要乘上这个A逆，然后这个打个圈之后，然后把这个消掉，对不对？",
    "language": "zh",
    "emotion": "neutral"
  },
  {
    "sentence_id": 325,
    "text": "所以你你这个你最后就等于要要算这个玩意。",
    "language": "zh",
    "emotion": "neutral"
  },
  {
    "sentence_id": 326,
    "text": "要算这个东西，，要算这个，要算这个东西这是什么意思？",
    "language": "zh",
    "emotion": "neutral"
  },
  {
    "sentence_id": 327,
    "text": "就等于要把这个A要解两次，因为这是个2×2的矩阵，就是要解两次，原来是原来是一个向量解一次，现在是现在你有两个SIV就等于要解两次，所以在这个地方你要把这个A解两次，解完了这个东西以后你还要解一次A，再把phi和谬算出来，所以这里就要解三次。",
    "language": "zh",
    "emotion": "neutral"
  },
  {
    "sentence_id": 328,
    "text": "你多了一个s i v，就要把这个a多减一次，所以这个运算量就是说稍微加大一点，多加一个s i v就多加一次。",
    "language": "zh",
    "emotion": "neutral"
  },
  {
    "sentence_id": 329,
    "text": "所以，所以我刚刚那个体积那里，我就能省一次就省一次，体积就把它放到线性里面去。",
    "language": "zh",
    "emotion": "neutral"
  },
  {
    "sentence_id": 330,
    "text": "你要把体积也放在这里也行，你等，但是你要多减一次。",
    "language": "zh",
    "emotion": "neutral"
  },
  {
    "sentence_id": 331,
    "text": "所以这个就等于说要把这个a每一步减三次就行了。",
    "language": "zh",
    "emotion": "neutral"
  },
  {
    "sentence_id": 332,
    "text": "那那剩下的这个东西都是都是常系数，所以这个都是常系数，你好解。，",
    "language": "zh",
    "emotion": "neutral"
  },
  {
    "sentence_id": 333,
    "text": "，尤其是这个玩意都是在周期边界条件下，周期边界条件的情况下做的话，你会发现这个东西，这个是，这个就是就是非常非常的简单，在周期边界这样情况下，这个这个管它是拉普拉斯还是拉普拉斯平方还是拉普拉斯的立方，管它是二阶、四阶、六阶算子，它都是对角阵，它都是对角阵，没有方程可解，所以可以算起来非常快，即使在这个。",
    "language": "zh",
    "emotion": "neutral"
  },
  {
    "sentence_id": 334,
    "text": "尤其。",
    "language": "zh",
    "emotion": "neutral"
  },
  {
    "sentence_id": 335,
    "text": "所以所以这个东西你即使算这个算这个什么三维的问题，那也也非常也可以非常快的就能算。",
    "language": "zh",
    "emotion": "neutral"
  },
  {
    "sentence_id": 336,
    "text": "那么这里就是随便给大家演示的，这这这，你比如说四个球，四。",
    "language": "zh",
    "emotion": "neutral"
  },
  {
    "sentence_id": 337,
    "text": "，是个是个小包囊，它在演化过程中，你假如不加这个，你假如不加这个，不加这个体积或这个表面积这个限制的话，没这个限制的话，它它就会它就会变成一个球，就会变成一个球。",
    "language": "zh",
    "emotion": "neutral"
  },
  {
    "sentence_id": 338,
    "text": "但是你加上这个表面积的和体积的限制的话，它这个它就有限制，它它这个它就会演变成演变成这个各种这个非常奇怪的这个形状，在某种参数情况下，它就会会变成这种花生的形状，或者变成这种甜甜圈的这种形状，这个都是在实验中实验中可以观测到的这种这种现象。",
    "language": "zh",
    "emotion": "neutral"
  },
  {
    "sentence_id": 339,
    "text": "所以这这种像这种这个三维的这个模拟，你你在这个用这种算法，你在你的这个笔记本上就就可以做。",
    "language": "zh",
    "emotion": "neutral"
  },
  {
    "sentence_id": 340,
    "text": "，那这个东西都是我后面要讲的，这个东西都是我后面要讲的，嗯，，要讲讲一个这个。",
    "language": "zh",
    "emotion": "neutral"
  },
  {
    "sentence_id": 341,
    "text": "OK，讲一个这个讲一个这个例子吧，就是就是这个SAB，一个这个SAB一个我觉得一个很重要的这个应用，现在还没有还没有太多这方面的工作，就是说你可以拿来做这个优化，你。",
    "language": "zh",
    "emotion": "neutral"
  },
  {
    "sentence_id": 342,
    "text": "你可以你可以拿它来做优化，因为优化是很大一类问题，包括现在机器学习，对吧？",
    "language": "zh",
    "emotion": "neutral"
  },
  {
    "sentence_id": 343,
    "text": "机器学习说到底就是个优化嘛，它什么优化问题？",
    "language": "zh",
    "emotion": "neutral"
  },
  {
    "sentence_id": 344,
    "text": "优化问题它就是有一个有一个cost function，对吧？",
    "language": "zh",
    "emotion": "neutral"
  },
  {
    "sentence_id": 345,
    "text": "要minimize这个cost function，那么这个你怎么minimize这个cost function？",
    "language": "zh",
    "emotion": "neutral"
  },
  {
    "sentence_id": 346,
    "text": "有有很多路可以走，那么这个SIV就是一条路，就是可以走的一条路，可以走的一条路。",
    "language": "zh",
    "emotion": "neutral"
  },
  {
    "sentence_id": 347,
    "text": "那么我这里给大家举一个例子。",
    "language": "zh",
    "emotion": "neutral"
  },
  {
    "sentence_id": 348,
    "text": "就是就是说，这个，我我做这个命题买这些怎么做？",
    "language": "zh",
    "emotion": "neutral"
  },
  {
    "sentence_id": 349,
    "text": "我有一个这个有一个能量，对吧？",
    "language": "zh",
    "emotion": "neutral"
  },
  {
    "sentence_id": 350,
    "text": "我有一个能量，我假如要想它的找它的最小最小能量解，我怎么做？",
    "language": "zh",
    "emotion": "neutral"
  },
  {
    "sentence_id": 351,
    "text": "我我我就是它的它的这个最小能量解就是德尔塔一德尔塔2=0，对不对？",
    "language": "zh",
    "emotion": "neutral"
  },
  {
    "sentence_id": 352,
    "text": "就德尔塔一德尔塔2=0，但是德尔塔一德尔塔2=0这个东西非常非线性也非凸，不好解。",
    "language": "zh",
    "emotion": "neutral"
  },
  {
    "sentence_id": 353,
    "text": "那不好解我怎么做呢？",
    "language": "zh",
    "emotion": "neutral"
  },
  {
    "sentence_id": 354,
    "text": "我可以把它写成一个，我可以加在一个虚拟的时间上去，那我可以加上一个虚拟的时间上去。",
    "language": "zh",
    "emotion": "neutral"
  },
  {
    "sentence_id": 355,
    "text": "就是我不解这个玩意儿，我不去解这个方程，我去解什么？",
    "language": "zh",
    "emotion": "neutral"
  },
  {
    "sentence_id": 356,
    "text": "我去解这个方程。",
    "language": "zh",
    "emotion": "neutral"
  },
  {
    "sentence_id": 357,
    "text": "我去解我们这个梯度流方程，然后这个 g 是你自己，g 就是你的选择了，你想走哪条路，让它走的比较快一点，这个这个就是就是经验了，那就这样。",
    "language": "zh",
    "emotion": "neutral"
  },
  {
    "sentence_id": 358,
    "text": "但是这个你让 t 趋向于无穷，它就。",
    "language": "zh",
    "emotion": "neutral"
  },
  {
    "sentence_id": 359,
    "text": "那就逼近于这个的解，所以这是一条路。",
    "language": "zh",
    "emotion": "neutral"
  },
  {
    "sentence_id": 360,
    "text": "它不，它有可能很多解，你这个没办法，你要想办法找它最小能量解，那你得是你用stochastic是不是什么什么关系了，那那是另外的事情。",
    "language": "zh",
    "emotion": "neutral"
  },
  {
    "sentence_id": 361,
    "text": "但是，但是起码我梯度下降一无穷，我它一定会收敛到收敛到嗯这个这个方程的一个解，对吧？",
    "language": "zh",
    "emotion": "neutral"
  },
  {
    "sentence_id": 362,
    "text": "所以你这个非凸的问题你不好解，我可以用这个梯度流的这个。",
    "language": "zh",
    "emotion": "neutral"
  },
  {
    "sentence_id": 363,
    "text": "梯度流的这个办法去求，那这个梯度流，那么写这个梯度流就可以用这个来写。",
    "language": "zh",
    "emotion": "neutral"
  },
  {
    "sentence_id": 364,
    "text": "那我给大家举一个例子。",
    "language": "zh",
    "emotion": "neutral"
  },
  {
    "sentence_id": 365,
    "text": "我给大家举个例子，这个这个例子就是就是在这个波子爱因斯坦这个康达效应，就算这个最小能量计算算这个算这个光子在这个这个波子爱因斯坦康达效应上面这个。",
    "language": "zh",
    "emotion": "neutral"
  },
  {
    "sentence_id": 366,
    "text": "这个这个例子，那么它的这个自由能，它的这个自由能就是就是这样子，它的这个自由能就是这样子。",
    "language": "zh",
    "emotion": "neutral"
  },
  {
    "sentence_id": 367,
    "text": "那么这里这个这个L分线性部分，一个就是。",
    "language": "zh",
    "emotion": "neutral"
  },
  {
    "sentence_id": 368,
    "text": "，一个一一个是就是我们通常的布拉巴斯，它另外还有一个给定的势能，这个这是一个给定的势能，一个确定的这个potential，给定的势能，然后它要满足，它要满足这个这个这么一个限制，就是它的这个这个模的平方积分要等于一，这个波函数呢它这个总的质量是守恒的。",
    "language": "zh",
    "emotion": "neutral"
  },
  {
    "sentence_id": 369,
    "text": "那这个时候你要找它的这个ground state，要找这个最小基态解，要找它的基态解的话，我就可以通过通过解这个梯度流来实现。",
    "language": "zh",
    "emotion": "neutral"
  },
  {
    "sentence_id": 370,
    "text": "我就会通过解梯度流来实现，对吧？",
    "language": "zh",
    "emotion": "neutral"
  },
  {
    "sentence_id": 371,
    "text": "我们写梯度流来实现，加上这个限制。",
    "language": "zh",
    "emotion": "neutral"
  },
  {
    "sentence_id": 372,
    "text": "通过解。",
    "language": "zh",
    "emotion": "neutral"
  },
  {
    "sentence_id": 373,
    "text": "那么梯度流加上这个限制怎么办呢？",
    "language": "zh",
    "emotion": "neutral"
  },
  {
    "sentence_id": 374,
    "text": "就是跟刚刚那个办法一样，对不对？",
    "language": "zh",
    "emotion": "neutral"
  },
  {
    "sentence_id": 375,
    "text": "我把这个限制，把这个限制用用这个用这个罚函数给它加上去。",
    "language": "zh",
    "emotion": "neutral"
  },
  {
    "sentence_id": 376,
    "text": "是吧，把这个限制用罚函数给它加上去，然后我引进两个，引进两个 S I D，一个是这个非线性项的 S I D，一个是这个这个这个罚函数的这个 S I D，然后你就照猫画虎，刚刚这个算法就就就可以用了，是吧？",
    "language": "zh",
    "emotion": "neutral"
  },
  {
    "sentence_id": 377,
    "text": "对，我们就可以用，就可以用，但是你就用的时候你会。",
    "language": "zh",
    "emotion": "neutral"
  },
  {
    "sentence_id": 378,
    "text": "好，OK，这是。",
    "language": "zh",
    "emotion": "neutral"
  },
  {
    "sentence_id": 379,
    "text": "就是你假如这个我再说说一句，就是说你假如只是做这个，你假如只是对这个只是对定长解感兴趣的话，你假如只是对定长解感兴趣的话，就没有必要用用什么二阶格式，高阶格式，就是用高阶格式你的收敛速度会更慢，就是你用一阶格式，用越粗糙的格式。",
    "language": "zh",
    "emotion": "neutral"
  },
  {
    "sentence_id": 380,
    "text": "它收敛到这个定长解的这个速度它越快，所以就用一阶格式就行了，不要去用这个二阶格式。",
    "language": "zh",
    "emotion": "neutral"
  },
  {
    "sentence_id": 381,
    "text": "你就用这个一阶格式去去算。",
    "language": "zh",
    "emotion": "neutral"
  },
  {
    "sentence_id": 382,
    "text": "那么这个一阶格式它这个算它这个好处是什么呢？",
    "language": "zh",
    "emotion": "neutral"
  },
  {
    "sentence_id": 383,
    "text": "它它这边这个好处就是它它能够保证你每一步这个能量一定是下降的。",
    "language": "zh",
    "emotion": "neutral"
  },
  {
    "sentence_id": 384,
    "text": "现在你其他那个机器学习或者什么这个办法，它它这个它没有办法保证它每一步能量下降。",
    "language": "zh",
    "emotion": "neutral"
  },
  {
    "sentence_id": 385,
    "text": "没有办法保证能量下降，但是保证每一步能量下降不一定是最好的算法。",
    "language": "zh",
    "emotion": "neutral"
  },
  {
    "sentence_id": 386,
    "text": "就是说它它它每一步下降，可能下降很慢，它有的时候涨快一点，它可能下降很快。",
    "language": "zh",
    "emotion": "neutral"
  },
  {
    "sentence_id": 387,
    "text": "所以这个这个到底哪个好哪个坏很难说，但是它这个好处什么好处？",
    "language": "zh",
    "emotion": "neutral"
  },
  {
    "sentence_id": 388,
    "text": "它肯定收敛，它一定会收敛到一个收敛到一个解，它一定收敛，它可能收敛比较慢，它一定会收敛的。",
    "language": "zh",
    "emotion": "neutral"
  },
  {
    "sentence_id": 389,
    "text": "所以所以这个这个它一定会收敛，但是但是我们发现就是说跟它原来的这个办法比，跟他这个原他们原来这个东西是怎么做的，原来我跟跟大家讲一下这个原来这个比较这个一个比较有效的办法去解这个玩意是怎么做，他就是用他就是用这个用用用这个。",
    "language": "zh",
    "emotion": "neutral"
  },
  {
    "sentence_id": 390,
    "text": "那个，他就是用这个用这个backward Euler这个方法去做。，",
    "language": "zh",
    "emotion": "neutral"
  },
  {
    "sentence_id": 391,
    "text": "欧拉方法去做，什么个意思呢？",
    "language": "zh",
    "emotion": "neutral"
  },
  {
    "sentence_id": 392,
    "text": "就是说我第一步我就解一个这样子的这个线性化的这个这个方程，你看对。",
    "language": "zh",
    "emotion": "neutral"
  },
  {
    "sentence_id": 393,
    "text": "对这个方程，对这个方程我去把我的欧拉，把这个非线性项线性化，它的思想也是一样的，非线性项线性化，因为不想解非线性方程组。",
    "language": "zh",
    "emotion": "neutral"
  },
  {
    "sentence_id": 394,
    "text": "变成线性化，然后，然后它怎么去满足？",
    "language": "zh",
    "emotion": "neutral"
  },
  {
    "sentence_id": 395,
    "text": "它怎么去满足这个模的？",
    "language": "zh",
    "emotion": "neutral"
  },
  {
    "sentence_id": 396,
    "text": "怎么去满足这个模的这个条件呢？",
    "language": "zh",
    "emotion": "neutral"
  },
  {
    "sentence_id": 397,
    "text": "满足模的条件就是说这个没办法满足模的条件，那在第二步它就做这个，就就就愣把它拉回来，做这个投影，就投影到模等于一的这个空间上。，",
    "language": "zh",
    "emotion": "neutral"
  },
  {
    "sentence_id": 398,
    "text": "所以它叫这个Bogomol'nyi-Prasad-Sandipan，那这个东西算起来。",
    "language": "zh",
    "emotion": "neutral"
  },
  {
    "sentence_id": 399,
    "text": "算起来不是最简单，但也还行，因为这里有个变形，它是它每一步是变形，就是说你要要要重新算这个这个这个这个每一步的这个矩阵都要重新算过。，",
    "language": "zh",
    "emotion": "neutral"
  },
  {
    "sentence_id": 400,
    "text": "它也没有办法保证这个每一步能量下降，这一步可以保证能量下降，但是一一投影以后能量就不下降，但是它这个可以算的比较快，可以。",
    "language": "zh",
    "emotion": "neutral"
  },
  {
    "sentence_id": 401,
    "text": "可以可以算的比较快，它的毛病毛病在哪里呢？",
    "language": "zh",
    "emotion": "neutral"
  },
  {
    "sentence_id": 402,
    "text": "这个毛病就是你只有一个分量做这个projection好做，一个分量做这个projection直接就这么做就完了。",
    "language": "zh",
    "emotion": "neutral"
  },
  {
    "sentence_id": 403,
    "text": "但是假如我这个是有好几个分量，假如我有好几个分量，它的这个限制是这个模的这个和的平方等于一的话。",
    "language": "zh",
    "emotion": "neutral"
  },
  {
    "sentence_id": 404,
    "text": "这个投影怎么做就不知道了，就不好做了。",
    "language": "zh",
    "emotion": "neutral"
  },
  {
    "sentence_id": 405,
    "text": "这这第二步这个投影怎么怎么投影就非常麻烦，不好做。",
    "language": "zh",
    "emotion": "neutral"
  },
  {
    "sentence_id": 406,
    "text": "所以所以这这个办法做一个分量还行，做多个分量不太好做。",
    "language": "zh",
    "emotion": "neutral"
  },
  {
    "sentence_id": 407,
    "text": "那现在我们这个办法和它。",
    "language": "zh",
    "emotion": "neutral"
  },
  {
    "sentence_id": 408,
    "text": "这个比较一下就会发现，你看这个是，因为现在现在这个，，现在我们唯一能够决定这个这个方法有效不有效的，就是说你走多少步它就收敛，然后误差是多少，然后这个每一步是什么运算量。",
    "language": "zh",
    "emotion": "neutral"
  },
  {
    "sentence_id": 409,
    "text": "要在这个10的负二次方的时候。",
    "language": "zh",
    "emotion": "neutral"
  },
  {
    "sentence_id": 410,
    "text": "哎，它这个才靠近了一点，但是这个时候那个步长就用的步长就多了，你一直要到这个10的负四次方，这个能量才算的稍微有点靠谱。，",
    "language": "zh",
    "emotion": "neutral"
  },
  {
    "sentence_id": 411,
    "text": "而且这个这个运算量就太大了，要要走这么多步才才才收敛，这个二阶格式也没有好多少，嗯，差不多的这个情况，所以这个和它比没有优势，那个和它比没有优势就是说我虽然这个保持。",
    "language": "zh",
    "emotion": "neutral"
  },
  {
    "sentence_id": 412,
    "text": "我我这个这个格式是每一步都是能量下降的，但是每一步这个能量下降的太少了，这个走的走的这个走走的有点慢，所以每一步能量下降不一定是最好的办法，那么。",
    "language": "zh",
    "emotion": "neutral"
  },
  {
    "sentence_id": 413,
    "text": "那么怎么样可以可以改进这件事情？",
    "language": "zh",
    "emotion": "neutral"
  },
  {
    "sentence_id": 414,
    "text": "就是S A V它有一个好有一个好处，就是说你这个修正的能量和原始的能量，对吧？",
    "language": "zh",
    "emotion": "neutral"
  },
  {
    "sentence_id": 415,
    "text": "我这个修正的能量和原始的能量差是你这个东西时间不长。",
    "language": "zh",
    "emotion": "neutral"
  },
  {
    "sentence_id": 416,
    "text": "够不够小的这个一个标准，一个标准就是说他们两个要差的很远，肯定是没算好。",
    "language": "zh",
    "emotion": "neutral"
  },
  {
    "sentence_id": 417,
    "text": "他们两个要靠得近，就说明还凑不一定不一定这个一定好，但是起码是一个标准。",
    "language": "zh",
    "emotion": "neutral"
  },
  {
    "sentence_id": 418,
    "text": "但是我有另外一个办法，就是说那我想，我就想让这个东西。",
    "language": "zh",
    "emotion": "neutral"
  },
  {
    "sentence_id": 419,
    "text": "特别靠近这个能量的话，我干脆我每算一步我就重新给它设定一下，我就把这个 S A D 就设定成这个原来的能量，我这个东西可以做嘛。",
    "language": "zh",
    "emotion": "neutral"
  },
  {
    "sentence_id": 420,
    "text": "所以我这是这个改改进的算法，这是第一步。",
    "language": "zh",
    "emotion": "neutral"
  },
  {
    "sentence_id": 421,
    "text": "第一步我算出一个这个。",
    "language": "zh",
    "emotion": "neutral"
  },
  {
    "sentence_id": 422,
    "text": "这个这个半n加一，这个算出两两个s a b，这个s a b这个东西跟原来的这个能量，跟原来这个能量东西没有什么关系的，对吧？",
    "language": "zh",
    "emotion": "neutral"
  },
  {
    "sentence_id": 423,
    "text": "但是我在走到下一步之前，我就令这个东西就等于它原来的能量，因为我这个东西已经算出来。",
    "language": "zh",
    "emotion": "neutral"
  },
  {
    "sentence_id": 424,
    "text": "是吧，我就可以设法等于它，我这个东西我就设法等于它，我总可以吧。",
    "language": "zh",
    "emotion": "neutral"
  },
  {
    "sentence_id": 425,
    "text": "然后我再转到下一步去，所以这也是一个格式。",
    "language": "zh",
    "emotion": "neutral"
  },
  {
    "sentence_id": 426,
    "text": "这个格式就是说我把这个SIV变了一下，就是第二步我就把把它用这个能量替换，那它有好处也有坏处，它的这个。",
    "language": "zh",
    "emotion": "neutral"
  },
  {
    "sentence_id": 427,
    "text": "坏处就是说我可以证明这一步的时候它的这个能量是下降的，我这步的时候能量是下降的。",
    "language": "zh",
    "emotion": "neutral"
  },
  {
    "sentence_id": 428,
    "text": "但是你这么一做了以后，它就把它这个能量结构破坏，那结构把它我就证明不了，跟跟他前面那个他这个办过的order projection一样，我也证明不了。",
    "language": "zh",
    "emotion": "neutral"
  },
  {
    "sentence_id": 429,
    "text": "我也证明不了它它这个每一步它这个能量下降，但是没有关系，我现在这个我不我这个能量下降不是我每一步能量下降不是我的终极目标的话，所以我我可以试试这么走到底行不行，那么。",
    "language": "zh",
    "emotion": "neutral"
  },
  {
    "sentence_id": 430,
    "text": "这样子一做，你就发现，哎，这样子一做这个效果就非常好。",
    "language": "zh",
    "emotion": "neutral"
  },
  {
    "sentence_id": 431,
    "text": "它的这个每一步的这个这个这个步数，基本上就是跟这个跟这个前面的这个 backward Euler projection 方法的这个步数和精度都是一样，步数和精度都是一样。",
    "language": "zh",
    "emotion": "neutral"
  },
  {
    "sentence_id": 432,
    "text": "就说你只要这个，只要40步就收敛到极态解，而且这个精度非常好。",
    "language": "zh",
    "emotion": "neutral"
  },
  {
    "sentence_id": 433,
    "text": "那它的好处什么？",
    "language": "zh",
    "emotion": "neutral"
  },
  {
    "sentence_id": 434,
    "text": "它的好处这每一步只需要解线性常系数方程，所以又比原来那个方法这个更有效。",
    "language": "zh",
    "emotion": "neutral"
  },
  {
    "sentence_id": 435,
    "text": "线性常系数方程，原来是线性变系数，是线性常系数。",
    "language": "zh",
    "emotion": "neutral"
  },
  {
    "sentence_id": 436,
    "text": "OK，这是在一个分量的情况下，所以这个对对原来的方法有了一点改进，不是很大的改进。",
    "language": "zh",
    "emotion": "neutral"
  },
  {
    "sentence_id": 437,
    "text": "那么最主要的是这个东西你可以做到哦，这里是一个就是说这个一这个这个这个这个惩罚系数的收敛收敛关系。",
    "language": "zh",
    "emotion": "neutral"
  },
  {
    "sentence_id": 438,
    "text": "说最主要的是这个你对这个多个。",
    "language": "zh",
    "emotion": "neutral"
  },
  {
    "sentence_id": 439,
    "text": "多个分量的话，它的这个优点，它这个优点才显示更更加显示出来。",
    "language": "zh",
    "emotion": "neutral"
  },
  {
    "sentence_id": 440,
    "text": "就说你好比考虑两个分量，它两个分量它要满足一个这样子的这个，这样子一个限制，这样子限制做做这个投影就不好投影，就不好投影。",
    "language": "zh",
    "emotion": "neutral"
  },
  {
    "sentence_id": 441,
    "text": "但是对于我们来讲，这个东西它的这个，，它它的这个。",
    "language": "zh",
    "emotion": "neutral"
  },
  {
    "sentence_id": 442,
    "text": "，做 S A D 是，做做 S A D 是是是同样简单的，做做 S A D 非常简单。",
    "language": "zh",
    "emotion": "neutral"
  },
  {
    "sentence_id": 443,
    "text": "我刚刚已经讲了，你不管是两个分量还是200个分量，都只要引进一个，另外加一个 S A D 就行。，",
    "language": "zh",
    "emotion": "neutral"
  },
  {
    "sentence_id": 444,
    "text": "所以你这里只有两个分量的话，那你就那你就引多再再引进一个，就引进一个这个 S A D 就就行了，对吧？",
    "language": "zh",
    "emotion": "neutral"
  },
  {
    "sentence_id": 445,
    "text": "你引进一个 S A D 处理这个非线性项，然后要引进一个 S A D 处理这个限制，引。",
    "language": "zh",
    "emotion": "neutral"
  },
  {
    "sentence_id": 446,
    "text": "引进SAP处理这个限制，然后你把这个梯度流用这个SAP改写，改写，然后剩下的剩下的就是蔡普斯的操作，对吧？",
    "language": "zh",
    "emotion": "neutral"
  },
  {
    "sentence_id": 447,
    "text": "剩下就是蔡普斯蔡普斯的操作，这个同样你也要你也要。",
    "language": "zh",
    "emotion": "neutral"
  },
  {
    "sentence_id": 448,
    "text": "不要用这个通常的这个S A B，你要算了一步以后，你你把这个你把这个东西就用它的这个原始能量来替代，用原始能量来替代，那么这样子的话就可以可以算的这个就是说对于某种S A B也可以算的非常好，也也可以算也可以算的非常好，可以算的，算起来非常有效。",
    "language": "zh",
    "emotion": "neutral"
  },
  {
    "sentence_id": 449,
    "text": "那么这是这个就是。",
    "language": "zh",
    "emotion": "neutral"
  },
  {
    "sentence_id": 450,
    "text": "这个就是一个例子，这个就是说做这个optimization呢，给大家讲了这个一个例子。",
    "language": "zh",
    "emotion": "neutral"
  },
  {
    "sentence_id": 451,
    "text": "那么，这个optimization这个东西当然当然很广，就是说你你什么样的这个，就是就是说我的感觉就是说你有非常多的这个这个优化的问题，你都可以用。",
    "language": "zh",
    "emotion": "neutral"
  },
  {
    "sentence_id": 452,
    "text": "类似的这种办法去算，那么你也可以考虑这个原始的这个S A V，也可以考虑这个这个像这种修正的S A V，就是说，可能对某种问题，某些问题，这个修正的S A V这个算起来更有效一点。",
    "language": "zh",
    "emotion": "neutral"
  },
  {
    "sentence_id": 453,
    "text": "那么这是这是我今天这个要讲的这个几个应用。",
    "language": "zh",
    "emotion": "neutral"
  },
  {
    "sentence_id": 454,
    "text": "那么明天。",
    "language": "zh",
    "emotion": "neutral"
  },
  {
    "sentence_id": 455,
    "text": "，还有一些这个更复杂的这个，讲强非线性怎么弄，这个我想我到最后一天再再给大家讲一点。",
    "language": "zh",
    "emotion": "neutral"
  },
  {
    "sentence_id": 456,
    "text": "那么从明天开始，我就从明天开始我就讲NS方程，明天讲NS方程，后天继续NS方程，并且开始这个降感模型，，最后。",
    "language": "zh",
    "emotion": "neutral"
  },
  {
    "sentence_id": 457,
    "text": "最后一天我们就要把这个梯度流，x方程、向量方程全部耦合在一起来解这个非常复杂的这个这个耗散气的。",
    "language": "zh",
    "emotion": "neutral"
  },
  {
    "sentence_id": 458,
    "text": "那么今天的作业，OK，今天的作业就是就是用这个今天今天就用这个二阶这个S A V格式去算这个算这个一维，算一维的就行。",
    "language": "zh",
    "emotion": "neutral"
  },
  {
    "sentence_id": 459,
    "text": "一维的这个S A V方这个这个方程，那么参数取什么东西呢？",
    "language": "zh",
    "emotion": "neutral"
  },
  {
    "sentence_id": 460,
    "text": "这个取。",
    "language": "zh",
    "emotion": "neutral"
  },
  {
    "sentence_id": 461,
    "text": "这个一斐就是这个1/2，这个规定斐的这个平方，加上这个一除上一什么平方，这个斐的平方减一的平方，然后取这个欧米伽就等于，它比如说-1~1吧，然后一什么取取，它比如说取00:02。",
    "language": "zh",
    "emotion": "neutral"
  },
  {
    "sentence_id": 462,
    "text": "然后这个大概要用点，大概要比较多，，先先先要快一点，00:05。",
    "language": "zh",
    "emotion": "neutral"
  },
  {
    "sentence_id": 463,
    "text": "取个00:05，然后你点点大概要取100个点左右，哎，取100个点。",
    "language": "zh",
    "emotion": "neutral"
  },
  {
    "sentence_id": 464,
    "text": "然后delta t这个，你这个delta t大概要你你要加上sub来，就是说你要用要分裂的时候要加一个那个s，这个你自己去自己去调一调，怎么弄怎么弄一弄看看怎么样算的。",
    "language": "zh",
    "emotion": "neutral"
  },
  {
    "sentence_id": 465,
    "text": "这个delta t有可能要取的什么10的负三什么10的多少，我也记不太清楚，自己自己自己调一调，然后初值。",
    "language": "zh",
    "emotion": "neutral"
  },
  {
    "sentence_id": 466,
    "text": "出值这个sin零x，sin零x你好比说就取这个什么sin派x，它它这个东西就是说就就是说开始假如是这样子的，它会它会慢慢变成慢慢慢慢变成这样子的，或或者是或者是这样子的，就是就是会慢慢。",
    "language": "zh",
    "emotion": "neutral"
  },
  {
    "sentence_id": 467,
    "text": "解只会变成一和负一，然后有一个有一个边界层，这个解你画出图来画成是画成是最后这个图大致是一和负一的这个有个边界，你大概就差不多就对了。",
    "language": "zh",
    "emotion": "neutral"
  },
  {
    "sentence_id": 468,
    "text": "就是那么你随便随便用什么。",
    "language": "zh",
    "emotion": "neutral"
  },
  {
    "sentence_id": 469,
    "text": "随便用，就是用待会那个陈胜辉，有没有，你们有没有，没给你，有没有一个，有个群是吧？，",
    "language": "zh",
    "emotion": "neutral"
  },
  {
    "sentence_id": 470,
    "text": "有个群，你把那个你你那个这个差分的差分的这个程序发给他，这个这个程序你大家自己也有，你要没有的话，你就用他这个，用用他这个差分程序试一试，好。",
    "language": "zh",
    "emotion": "neutral"
  },
  {
    "sentence_id": 471,
    "text": "好，那今天就是今天今天这个下午的这个作业就这个完成。",
    "language": "zh",
    "emotion": "neutral"
  }
]